testysynfoo/__init__.py
testysynfoo/hello.py
testiersynfoo-0.1.dist-info/METADATA
testiersynfoo-0.1.dist-info/WHEEL
testiersynfoo-0.1.dist-info/top_level.txt
testiersynfoo-0.1.dist-info/RECORD
