Metadata-Version: 2.1
Name: testiersynfoo
Version: 0.1
Summary: Request package
Author: synfosec
Author-email: <thesyndikit@proton.me>
Classifier: Programming Language :: Python :: 3
Classifier: Operating System :: Unix
Classifier: Operating System :: MacOS :: MacOS X
Classifier: Operating System :: Microsoft :: Windows
